{"P5": {"labels": ["documentation"], "postTitle": "\u4ec0\u4e48\u662f\u70b9\u4e91\u6570\u636e\uff1f", "postUrl": "post/shen-me-shi-dian-yun-shu-ju-%EF%BC%9F.html", "createdDate": "2026-04-14", "dateLabelColor": "#1f883d"}, "P4": {"labels": ["documentation"], "postTitle": "\u8fd9\u662f\u4e00\u6b21\u6d4b\u8bd5", "postUrl": "post/zhe-shi-yi-ci-ce-shi.html", "createdDate": "2026-03-25", "dateLabelColor": "#1f883d"}, "P2": {"labels": ["documentation"], "postTitle": "cuda\u5f52\u7ea6\u7b97\u6cd5\u7684\u753b\u9762\u611f\u63a8\u6f14", "postUrl": "post/cuda-gui-yue-suan-fa-de-hua-mian-gan-tui-yan.html", "createdDate": "2026-03-25", "dateLabelColor": "#1f883d"}, "labelColorDict": {"bug": "#d73a4a", "documentation": "#0075ca", "duplicate": "#cfd3d7", "enhancement": "#a2eeef", "good first issue": "#7057ff", "help wanted": "#008672", "invalid": "#e4e669", "question": "#d876e3", "wontfix": "#ffffff"}}